{
  "resolvedId": "/Users/eliasalerno/GitHub/Cuby/node_modules/d3-scale/src/index.js",
  "transforms": [
    {
      "name": "vite:load-fallback",
      "result": "export {\n  default as scaleBand,\n  point as scalePoint\n} from \"./band.js\";\n\nexport {\n  default as scaleIdentity\n} from \"./identity.js\";\n\nexport {\n  default as scaleLinear\n} from \"./linear.js\";\n\nexport {\n  default as scaleLog\n} from \"./log.js\";\n\nexport {\n  default as scaleSymlog\n} from \"./symlog.js\";\n\nexport {\n  default as scaleOrdinal,\n  implicit as scaleImplicit\n} from \"./ordinal.js\";\n\nexport {\n  default as scalePow,\n  sqrt as scaleSqrt\n} from \"./pow.js\";\n\nexport {\n  default as scaleRadial\n} from \"./radial.js\";\n\nexport {\n  default as scaleQuantile\n} from \"./quantile.js\";\n\nexport {\n  default as scaleQuantize\n} from \"./quantize.js\";\n\nexport {\n  default as scaleThreshold\n} from \"./threshold.js\";\n\nexport {\n  default as scaleTime\n} from \"./time.js\";\n\nexport {\n  default as scaleUtc\n} from \"./utcTime.js\";\n\nexport {\n  default as scaleSequential,\n  sequentialLog as scaleSequentialLog,\n  sequentialPow as scaleSequentialPow,\n  sequentialSqrt as scaleSequentialSqrt,\n  sequentialSymlog as scaleSequentialSymlog\n} from \"./sequential.js\";\n\nexport {\n  default as scaleSequentialQuantile\n} from \"./sequentialQuantile.js\";\n\nexport {\n  default as scaleDiverging,\n  divergingLog as scaleDivergingLog,\n  divergingPow as scaleDivergingPow,\n  divergingSqrt as scaleDivergingSqrt,\n  divergingSymlog as scaleDivergingSymlog\n} from \"./diverging.js\";\n\nexport {\n  default as tickFormat\n} from \"./tickFormat.js\";\n",
      "start": 1707675067287,
      "end": 1707675067345,
      "sourcemaps": null
    },
    {
      "name": "nuxt:layer-aliasing",
      "start": 1707675067345,
      "end": 1707675067345,
      "order": "pre"
    },
    {
      "name": "nuxt:server-devonly:transform",
      "start": 1707675067345,
      "end": 1707675067345,
      "order": "pre"
    },
    {
      "name": "nuxt:client-fallback-auto-id",
      "start": 1707675067345,
      "end": 1707675067345,
      "order": "pre"
    },
    {
      "name": "vite:css",
      "start": 1707675067345,
      "end": 1707675067345,
      "order": "normal"
    },
    {
      "name": "vite:esbuild",
      "start": 1707675067345,
      "end": 1707675067345,
      "order": "normal"
    },
    {
      "name": "vite:json",
      "start": 1707675067345,
      "end": 1707675067345,
      "order": "normal"
    },
    {
      "name": "vite:worker",
      "start": 1707675067345,
      "end": 1707675067345,
      "order": "normal"
    },
    {
      "name": "vite:vue",
      "start": 1707675067345,
      "end": 1707675067345,
      "order": "normal"
    },
    {
      "name": "vite:vue-jsx",
      "start": 1707675067345,
      "end": 1707675067345,
      "order": "normal"
    },
    {
      "name": "replace",
      "start": 1707675067345,
      "end": 1707675067345,
      "order": "normal"
    },
    {
      "name": "nuxt:remove-plugin-metadata",
      "start": 1707675067345,
      "end": 1707675067345,
      "order": "normal"
    },
    {
      "name": "nuxt:chunk-error",
      "start": 1707675067345,
      "end": 1707675067345,
      "order": "normal"
    },
    {
      "name": "nuxt:components:imports",
      "start": 1707675067345,
      "end": 1707675067345,
      "order": "normal"
    },
    {
      "name": "replace",
      "start": 1707675067345,
      "end": 1707675067345,
      "order": "normal"
    },
    {
      "name": "ssr-styles",
      "start": 1707675067345,
      "end": 1707675067345,
      "order": "normal"
    },
    {
      "name": "vite:define",
      "start": 1707675067345,
      "end": 1707675067345,
      "order": "normal"
    },
    {
      "name": "vite:css-post",
      "start": 1707675067345,
      "end": 1707675067345,
      "order": "normal"
    },
    {
      "name": "vite:build-html",
      "start": 1707675067345,
      "end": 1707675067345,
      "order": "normal"
    },
    {
      "name": "vite:worker-import-meta-url",
      "start": 1707675067345,
      "end": 1707675067345,
      "order": "normal"
    },
    {
      "name": "vite:asset-import-meta-url",
      "start": 1707675067345,
      "end": 1707675067345,
      "order": "normal"
    },
    {
      "name": "commonjs",
      "start": 1707675067345,
      "end": 1707675067345,
      "order": "normal"
    },
    {
      "name": "vite:dynamic-import-vars",
      "start": 1707675067345,
      "end": 1707675067345,
      "order": "normal"
    },
    {
      "name": "vite:import-glob",
      "start": 1707675067345,
      "end": 1707675067345,
      "order": "normal"
    },
    {
      "name": "nuxt:composable-keys",
      "start": 1707675067345,
      "end": 1707675067345,
      "order": "post"
    },
    {
      "name": "nuxt:imports-transform",
      "start": 1707675067345,
      "end": 1707675067345,
      "order": "post"
    },
    {
      "name": "unctx:transform",
      "start": 1707675067345,
      "end": 1707675067345,
      "order": "post"
    },
    {
      "name": "nuxt:runtime-paths-dep",
      "start": 1707675067345,
      "end": 1707675067345,
      "order": "post"
    },
    {
      "name": "nuxt:components-loader",
      "start": 1707675067345,
      "end": 1707675067345,
      "order": "post"
    },
    {
      "name": "nuxt:tree-shake-composables:transform",
      "start": 1707675067345,
      "end": 1707675067345,
      "order": "post"
    },
    {
      "name": "vite:build-import-analysis",
      "start": 1707675067345,
      "end": 1707675067345,
      "order": "normal"
    },
    {
      "name": "vite:reporter",
      "start": 1707675067345,
      "end": 1707675067345,
      "order": "normal"
    }
  ]
}
